nanophaser/__init__.py
nanophaser/cli.py
nanophaser/hapcon_lib.py
nanophaser/longshot_lib.py
nanophaser/phaser_lib.py
nanophaser/run_blast.py
nanophaser/run_minimap.py
nanophaser/utils.py
nanophaser/whatshap_lib.py
nanophaser/data/bola-original-alleles.fa
nanophaser/data/bola-original-alleles.fa.fai
nanophaser/data/bola-truncated-allele.fasta
nanophaser/data/bola_genome.fa
nanophaser/data/bola_genome.fa.fai
nanophaser/data/eval_genome.fa
nanophaser/data/test_reads.fq.gz
nanophaser-0.2.1.post0.dist-info/METADATA
nanophaser-0.2.1.post0.dist-info/WHEEL
nanophaser-0.2.1.post0.dist-info/entry_points.txt
nanophaser-0.2.1.post0.dist-info/top_level.txt
nanophaser-0.2.1.post0.dist-info/RECORD
