Metadata-Version: 2.4
Name: nanophaser
Version: 0.2.1.post0
Requires-Python: >=3.10
Requires-Dist: click
Requires-Dist: pysam
Requires-Dist: tqdm
Requires-Dist: cyvcf2
Requires-Dist: pyfaidx
Requires-Dist: pandas
Requires-Dist: biopython
